setup.py
rackup/__init__.py
rackup/rackup.py
rackup.egg-info/PKG-INFO
rackup.egg-info/SOURCES.txt
rackup.egg-info/dependency_links.txt
rackup.egg-info/entry_points.txt
rackup.egg-info/requires.txt
rackup.egg-info/top_level.txt
rackup.egg-info/zip-safe