Metadata-Version: 1.0
Name: rackup
Version: 1.0.0
Summary: Script for uploading files to Rackspace Cloud Files
Home-page: http://dryan.github.io/rackup
Author: Daniel Ryan
Author-email: dryan@dryan.com
License: MIT License
Platform: UNKNOWN
